discogs_cli/__init__.py
discogs_cli/completions.py
discogs_cli/discogs.py
discogs_cli/main.py
discogs_cli/main_cli.py
discogs_cli/pyglexer.py
discogs_cli/ext/__init__.py
discogs_cli/ext/completer.py
discogs_cli/ext/utils.py
discogs_cli_savoy1211-1.1.0.dist-info/LICENSE
discogs_cli_savoy1211-1.1.0.dist-info/METADATA
discogs_cli_savoy1211-1.1.0.dist-info/WHEEL
discogs_cli_savoy1211-1.1.0.dist-info/entry_points.txt
discogs_cli_savoy1211-1.1.0.dist-info/top_level.txt
discogs_cli_savoy1211-1.1.0.dist-info/RECORD
