Metadata-Version: 2.1
Name: discogs-cli-savoy1211
Version: 1.1.0
Summary: View and search for artists, labels and releases in the Discogs.com library, from the command line.
Home-page: https://github.com/savoy1211/discogs-cli
Author: Ryan Lee
Author-email: ryanlee250@gmail.com
License: MIT
Platform: UNKNOWN
Classifier: Environment :: Console
Classifier: Development Status :: 5 - Production/Stable
Classifier: Programming Language :: Python :: 2.6
Classifier: Programming Language :: Python :: 2.7
Classifier: License :: OSI Approved :: MIT License
Classifier: Operating System :: OS Independent
Requires-Dist: Pygments (==2.2.0)
Requires-Dist: click (==6.7)
Requires-Dist: discogs-client (==2.2.1)
Requires-Dist: prompt-toolkit (==1.0.13)
Requires-Dist: requests (==2.20.0)
